Metadata-Version: 2.1
Name: biliemoji
Version: 1.2.0
Summary: A simple Python library for accessing bilibili emojis and dresses.
Author: gcnanmu
Author-email: 
Maintainer: gcnanmu
License: MIT
Keywords: python,bilibili
Classifier: Development Status :: 1 - Planning
Classifier: License :: OSI Approved :: MIT License
Classifier: Intended Audience :: Developers
Classifier: Natural Language :: Chinese (Simplified)
Classifier: Programming Language :: Python :: 3.11
Classifier: Operating System :: Unix
Classifier: Operating System :: MacOS :: MacOS X
Classifier: Operating System :: Microsoft :: Windows
